uv_to_pipfile/__init__.py
uv_to_pipfile/__main__.py
uv_to_pipfile/_version.py
uv_to_pipfile/py.typed
uv_to_pipfile/uv_to_pipfile.py
uv_to_pipfile/uv_to_pipfile2.py
uv_to_pipfile-0.0.7.dist-info/METADATA
uv_to_pipfile-0.0.7.dist-info/WHEEL
uv_to_pipfile-0.0.7.dist-info/entry_points.txt
uv_to_pipfile-0.0.7.dist-info/licenses/LICENSE.txt
uv_to_pipfile-0.0.7.dist-info/RECORD
