Metadata-Version: 2.4
Name: uv-to-pipfile
Version: 0.0.7
Summary: A tool to convert uv.lock files to Pipfile.lock.
Project-URL: Documentation, https://github.com/FlavioAmurrioCS/uv-to-pipfile#readme
Project-URL: Issues, https://github.com/FlavioAmurrioCS/uv-to-pipfile/issues
Project-URL: Source, https://github.com/FlavioAmurrioCS/uv-to-pipfile
Author-email: Flavio Amurrio <25621374+FlavioAmurrioCS@users.noreply.github.com>
License-Expression: MIT
License-File: LICENSE.txt
Keywords: Pipfile.lock,dependency management,hook,pre-commit,python,uv.lock
Classifier: Development Status :: 4 - Beta
Classifier: Programming Language :: Python
Classifier: Programming Language :: Python :: 3.9
Classifier: Programming Language :: Python :: 3.10
Classifier: Programming Language :: Python :: 3.11
Classifier: Programming Language :: Python :: 3.12
Classifier: Programming Language :: Python :: 3.13
Classifier: Programming Language :: Python :: 3.14
Classifier: Programming Language :: Python :: Implementation :: CPython
Classifier: Programming Language :: Python :: Implementation :: PyPy
Requires-Python: >=3.9
Requires-Dist: tomli>=1.1.0; python_full_version < '3.11'
Requires-Dist: uv
Provides-Extra: tests
Requires-Dist: persistent-cache-decorator; extra == 'tests'
Requires-Dist: pipenv; extra == 'tests'
Requires-Dist: pytest; extra == 'tests'
Requires-Dist: tomli; (python_version < '3.11') and extra == 'tests'
Requires-Dist: uv; extra == 'tests'
Provides-Extra: types
Requires-Dist: mypy; extra == 'types'
Requires-Dist: persistent-cache-decorator; extra == 'types'
Requires-Dist: pipenv; extra == 'types'
Requires-Dist: pyrefly; extra == 'types'
Requires-Dist: pyright[nodejs]; extra == 'types'
Requires-Dist: pytest; extra == 'types'
Requires-Dist: tomli; (python_version < '3.11') and extra == 'types'
Requires-Dist: ty; extra == 'types'
Requires-Dist: typing-extensions; extra == 'types'
Requires-Dist: uv; extra == 'types'
